fifacodes/__init__.py
fifacodes/custom.csv
fifacodes/default.csv
fifacodes/py.typed
fifacodes-0.1.4.dist-info/LICENSE
fifacodes-0.1.4.dist-info/METADATA
fifacodes-0.1.4.dist-info/WHEEL
fifacodes-0.1.4.dist-info/RECORD
