Metadata-Version: 2.1
Name: fifacodes
Version: 0.1.4
Summary: FIFA member associations codes query and search.
Home-page: https://github.com/tanzhijian/fifacodes
License: MIT
Author: tanzhijian
Author-email: tanzhijianorg@outlook.com
Requires-Python: >=3.10
Classifier: License :: OSI Approved :: MIT License
Classifier: Programming Language :: Python :: 3
Classifier: Programming Language :: Python :: 3.10
Classifier: Programming Language :: Python :: 3.11
Classifier: Programming Language :: Python :: 3.12
Requires-Dist: rapidfuzz (>=3.6.1,<4.0.0)
Project-URL: Repository, https://github.com/tanzhijian/fifacodes
